nebulgym/__init__.py
nebulgym/base.py
nebulgym/data/__init__.py
nebulgym/data/bagua_dataset.py
nebulgym/data/base.py
nebulgym/data/nebuly_dataset.py
nebulgym/decorators/__init__.py
nebulgym/decorators/helpers.py
nebulgym/decorators/torch_decorators.py
nebulgym/patches/__init__.py
nebulgym/patches/pytorch/__init__.py
nebulgym/patches/pytorch/meprop_linear.py
nebulgym/training_learners/__init__.py
nebulgym/training_learners/base.py
nebulgym/training_learners/model_engines/__init__.py
nebulgym/training_learners/model_engines/base.py
nebulgym/training_learners/model_engines/ort_engine.py
nebulgym/training_learners/model_engines/rammer_engine.py
nebulgym/training_learners/model_engines/torch_engine.py
nebulgym/training_learners/model_engines/utils.py
nebulgym-0.1.1.dist-info/LICENSE
nebulgym-0.1.1.dist-info/METADATA
nebulgym-0.1.1.dist-info/WHEEL
nebulgym-0.1.1.dist-info/top_level.txt
nebulgym-0.1.1.dist-info/RECORD
