Metadata-Version: 2.1
Name: nebulgym
Version: 0.1.1
License-File: LICENSE
Requires-Dist: torch (>=1.10.0)
Requires-Dist: psutil (>=5.9.0)
